setup.py
FlagCapture/CaptureTheFlagServer.py
FlagCapture/Game.py
FlagCapture/__init__.py
FlagCapture/_game.py
FlagCapture/build.py
FlagCapture/buildBuilder.py
FlagCapture/entity.py
FlagCapture/math.py
FlagCapture/miniworld.py
FlagCapture/objmesh.py
FlagCapture/opengl.py
FlagCapture/params.py
FlagCapture/utils.py
FlagCapture/wrappers.py
FlagCapture.egg-info/PKG-INFO
FlagCapture.egg-info/SOURCES.txt
FlagCapture.egg-info/dependency_links.txt
FlagCapture.egg-info/top_level.txt
FlagCapture.egg-info/zip-safe