Metadata-Version: 2.1
Name: FlagCapture
Version: 0.2.0
Summary: A 3d Game that no-one can play unless Michael says so
Home-page: https://pypi.org/search/?q=FlagCapture
Download-URL: https://pypi.org/search/?q=FlagCapture
Author: Michael Caggeso
Author-email: laurencaggeso@gmail.com
License: Michael`s License
